MANIFEST.in
setup.py
django_location_picker.egg-info/PKG-INFO
django_location_picker.egg-info/SOURCES.txt
django_location_picker.egg-info/dependency_links.txt
django_location_picker.egg-info/requires.txt
django_location_picker.egg-info/top_level.txt
location_picker/__init__.py
location_picker/fields.py
location_picker/widgets.py
location_picker/static/css/location_picker.css
location_picker/static/js/location_picker.js
location_picker/static/scss/location_picker.scss