Metadata-Version: 1.0
Name: django-location-picker
Version: 0.1.0
Summary: A location picker field for the Django admin
Home-page: https://github.com/jamesfoley/django-location-picker
Author: James Foley
Author-email: jamesfoley@onespacemedia.com
License: UNKNOWN
Platform: any
